compynator/__init__.py
compynator/core.py
compynator/niceties.py
compynator-0.1.2.dist-info/LICENSE.txt
compynator-0.1.2.dist-info/WHEEL
compynator-0.1.2.dist-info/METADATA
compynator-0.1.2.dist-info/RECORD
