Metadata-Version: 2.1
Name: compynator
Version: 0.1.2
Summary: A pure Python implementation of parser combinators with asymptotically best performance and support for context-sensitive or ambiguous grammars.
Home-page: https://github.com/TheTerminalTemplar/compynator
License: Apache-2.0
Keywords: parser,functional,parser combinator,python
Author: google
Requires-Python: >=3.6,<4.0
Classifier: License :: OSI Approved :: Apache Software License
Classifier: Programming Language :: Python :: 3
Classifier: Programming Language :: Python :: 3.6
Classifier: Programming Language :: Python :: 3.7
Classifier: Programming Language :: Python :: 3.8
Project-URL: Documentation, https://compynator.readthedocs.io
Project-URL: Repository, https://github.com/TheTerminalTemplar/compynator
